panduza/__init__.py
panduza/pipe/__init__.py
panduza/pipe/alias.py
panduza/pipe/io.py
panduza/pipe/server.py
panduza_pipe-0.0.1.dist-info/METADATA
panduza_pipe-0.0.1.dist-info/WHEEL
panduza_pipe-0.0.1.dist-info/top_level.txt
panduza_pipe-0.0.1.dist-info/RECORD
