Metadata-Version: 2.1
Name: panduza-pipe
Version: 0.0.1
Summary: Wrapper for Panduza REST API Calls
Home-page: UNKNOWN
Author: Panduza Team
Author-email: panduza.team@gmail.com
License: UNKNOWN
Keywords: python,first package
Platform: UNKNOWN
Classifier: Development Status :: 3 - Alpha
Classifier: Intended Audience :: Education
Classifier: Programming Language :: Python :: 2
Classifier: Programming Language :: Python :: 3
Classifier: Operating System :: POSIX
Classifier: Operating System :: MacOS :: MacOS X
Classifier: Operating System :: Microsoft :: Windows
